<?xml version="1.0" encoding="UTF-8"?>
<root>
  <xsd:schema xmlns:xsd="http://www.w3.org/2001/XMLSchema" xmlns="" id="root">
    <xsd:element name="string">
      <xsd:complexType>
        <xsd:attribute name="key" use="required" type="xsd:string"/>
        <xsd:attribute id="en-US" name="en" use="required" type="xsd:string"/>
        <xsd:attribute id="fr-FR" name="fr" use="required" type="xsd:string"/>
      </xsd:complexType>
    </xsd:element>
  </xsd:schema>

  <!-- Pages -->
  <string key="pageHomeTitle" en="Home" fr="Accueil" />

</root>
